package1/Task1.py
package1/Task2.py
package1/Task3_a.py
package1/Task3_b.py
package1/Task4_a.py
package1/__init__.py
package2/Task5.py
package2/Task6.py
package2/Task7_a.py
package2/Task7_b.py
package2/Task8.py
package2/__init__.py
package3/Task10.py
package3/Task9.py
package3/__init__.py
taskpackagelib-0.0.1.dist-info/LICENSE.txt
taskpackagelib-0.0.1.dist-info/METADATA
taskpackagelib-0.0.1.dist-info/WHEEL
taskpackagelib-0.0.1.dist-info/entry_points.txt
taskpackagelib-0.0.1.dist-info/top_level.txt
taskpackagelib-0.0.1.dist-info/RECORD
