Metadata-Version: 2.1
Name: taskpackagelib
Version: 0.0.1
Summary: A library with package
Author: ThMeyerNeu
Author-email: <egor767680@gmial.com>
License: BSD 3-Clause License
Keywords: python
Classifier: Intended Audience :: Developers
Classifier: Programming Language :: Python :: 3
Classifier: Operating System :: Unix
Classifier: Operating System :: Microsoft :: Windows
License-File: LICENSE.txt
Requires-Dist: requests
Requires-Dist: importlib-metadata ; python_version < "3.8"
Provides-Extra: pdf
Requires-Dist: ReportLab (>=1.2) ; extra == 'pdf'
Requires-Dist: RXP ; extra == 'pdf'
Provides-Extra: rest
Requires-Dist: docutils (>=0.3) ; extra == 'rest'
Requires-Dist: pack (==1.1,==1.3) ; extra == 'rest'
